airflow_provider_iris/__init__.py
airflow_provider_iris/hooks/__init__.py
airflow_provider_iris/hooks/iris_hook.py
airflow_provider_iris/operators/__init__.py
airflow_provider_iris/operators/iris_operator.py
airflow_provider_iris/sensors/__init__.py
airflow_provider_iris/sensors/iris_sensor.py
airflow_provider_iris-1.3.9.dist-info/licenses/LICENSE
airflow_provider_iris-1.3.9.dist-info/METADATA
airflow_provider_iris-1.3.9.dist-info/WHEEL
airflow_provider_iris-1.3.9.dist-info/entry_points.txt
airflow_provider_iris-1.3.9.dist-info/top_level.txt
airflow_provider_iris-1.3.9.dist-info/RECORD
