Metadata-Version: 2.4
Name: airflow-provider-iris
Version: 1.3.9
Summary: airflow provider for intersystems
Home-page: https://github.com/mwaseem75
Author: Muhammad Waseem
Author-email: muhammadwas@outlook.com
License: Apache License 2.0
Classifier: Framework :: Apache Airflow
Classifier: Framework :: Apache Airflow :: Provider
Requires-Python: ~=3.7
License-File: LICENSE
Requires-Dist: apache-airflow>=2.0
Requires-Dist: sqlalchemy-iris
Requires-Dist: pandas
Dynamic: author
Dynamic: author-email
Dynamic: classifier
Dynamic: description
Dynamic: description-content-type
Dynamic: home-page
Dynamic: license
Dynamic: license-file
Dynamic: requires-dist
Dynamic: requires-python
Dynamic: summary
